[
  {
    "question": "For a particulary single seat glider, the maximum permissible gross weight is 715 lb. The C of G limits are 90-96 inches aft of the datum. The empty glider weighs 500 lb with moment 49,000, the pilot is at 70 inches from the datum with moment 11,200, and a ballast of 40 lb is 70 inches from the datum. Loaded as described, the",
    "answers": ["C of G is at the aft limit.",
                "C of G is at the forward limit.",
                "gross weight is exceeded.",
                "gross weight is 715 lb."
                ],
    "correctAnswerIndex": 1,
    "correctAnswerText": "Correct!"
  },
  {
    "question": "While on tow a glider pilot is unable to release the tow rope. The signal to indicate this condition to the tow pilot is to",
    "answers": ["yaw the glider to the right and left in a series of skidding turns.",
                "commence a series of 'S' turns at normal tow position.",
                "porpoise rapidly between high and low tow positions.",
                "fly to the left of the tug and rock the glider's wings."
                ],
    "correctAnswerIndex": 3,
    "correctAnswerText": "Correct!"
  },
  {
    "question": "A 'weak link' would most likely be associated with a",
    "answers": ["tow line.",
                "control cable.",
                "dive brake.",
                "canopy latch."
                ],
    "correctAnswerIndex": 0,
    "correctAnswerText": "Correct!"
  },
  {
    "question": "At a gliding ratio of 15:1, a glider descending 1,000 feet in still air will move forward a distance closest to",
    "answers": ["2.2 nm.",
                "2.5 nm.",
                "2.8 nm.",
                "3.1 nm."
                ],
    "correctAnswerIndex": 1,
    "correctAnswerText": "Correct!"    
  },
  {
    "question": "During ground operations if someone stands with both hands above their head, this means",
    "answers": ["number two for take off.",
                "take up slack.",
                "stop.",
                "begin take-off."
                ],
    "correctAnswerIndex": 2,
    "correctAnswerText": "Correct!"
  }
]